deluge_gui/__init__.py
deluge_gui/app_state.py
deluge_gui/card_views.py
deluge_gui/config.py
deluge_gui/deluge_gui.py
deluge_gui/event_handlers.py
deluge_gui/kit_views.py
deluge_gui/sample_views.py
deluge_gui/settings_window.py
deluge_gui/song_views.py
deluge_gui/synth_views.py
deluge_gui/windows.py
deluge_gui-0.1.1.dist-info/entry_points.txt
deluge_gui-0.1.1.dist-info/LICENSE
deluge_gui-0.1.1.dist-info/WHEEL
deluge_gui-0.1.1.dist-info/METADATA
deluge_gui-0.1.1.dist-info/RECORD
